{
  "errors": [],
  "warnings": [],
  "version": "4.43.0",
  "hash": "0ca1ee570fef4f0856c0",
  "publicPath": "/web/",
  "outputPath": "C:\\Workspace\\react-ssr-skeleton\\dist\\web",
  "assetsByChunkName": {
    "Footer": "Footer.js",
    "Header": "Header.js",
    "Home": "Home.js",
    "News": "News.js",
    "main": "main.js",
    "vendors~News": "vendors~News.js"
  },
  "assets": [
    {
      "name": "Footer.js",
      "size": 1773,
      "chunks": [
        "Footer"
      ],
      "chunkNames": [
        "Footer"
      ],
      "info": {},
      "emitted": false
    },
    {
      "name": "Header.js",
      "size": 2277,
      "chunks": [
        "Header"
      ],
      "chunkNames": [
        "Header"
      ],
      "info": {},
      "emitted": false
    },
    {
      "name": "Home.js",
      "size": 1672,
      "chunks": [
        "Home"
      ],
      "chunkNames": [
        "Home"
      ],
      "info": {},
      "emitted": false
    },
    {
      "name": "News.js",
      "size": 2947,
      "chunks": [
        "News"
      ],
      "chunkNames": [
        "News"
      ],
      "info": {},
      "emitted": false
    },
    {
      "name": "main.js",
      "size": 1355263,
      "chunks": [
        "main"
      ],
      "chunkNames": [
        "main"
      ],
      "info": {},
      "emitted": false
    },
    {
      "name": "vendors~News.js",
      "size": 103876,
      "chunks": [
        "vendors~News"
      ],
      "chunkNames": [
        "vendors~News"
      ],
      "info": {},
      "emitted": false
    }
  ],
  "filteredAssets": 0,
  "entrypoints": {
    "main": {
      "chunks": [
        "main"
      ],
      "assets": [
        "main.js"
      ],
      "children": {},
      "childAssets": {}
    }
  },
  "namedChunkGroups": {
    "main": {
      "chunks": [
        "main"
      ],
      "assets": [
        "main.js"
      ],
      "children": {},
      "childAssets": {}
    },
    "Header": {
      "chunks": [
        "Header"
      ],
      "assets": [
        "Header.js"
      ],
      "children": {},
      "childAssets": {}
    },
    "Footer": {
      "chunks": [
        "Footer"
      ],
      "assets": [
        "Footer.js"
      ],
      "children": {},
      "childAssets": {}
    },
    "News": {
      "chunks": [
        "vendors~News",
        "News"
      ],
      "assets": [
        "vendors~News.js",
        "News.js"
      ],
      "children": {},
      "childAssets": {}
    },
    "Home": {
      "chunks": [
        "Home"
      ],
      "assets": [
        "Home.js"
      ],
      "children": {},
      "childAssets": {}
    }
  },
  "logging": {
    "webpack.buildChunkGraph.visitModules": {
      "entries": [],
      "filteredEntries": 5,
      "debug": false
    }
  },
  "children": []
}